cykit/__init__.py
cykit/common.cpp
cykit/common.cpython-313-aarch64-linux-gnu.so
cykit/common.pxd
cykit/common.pyx
cykit/cylogger/CMakeLists.txt
cykit/cylogger/__init__.pxd
cykit/cylogger/__init__.py
cykit/cylogger/__init__.pyi
cykit/cylogger/color.pxd
cykit/cylogger/color.py
cykit/cylogger/cylogger.cpp
cykit/cylogger/cylogger.cpython-313-aarch64-linux-gnu.so
cykit/cylogger/cylogger.pxd
cykit/cylogger/cylogger.pyx
cykit/cylogger/libcylogger.so
cykit/cylogger/libcylogger.so.0
cykit/cylogger/libcylogger.so.0.0.12
cykit/cylogger/spdlog_logger.cpp
cykit/cylogger/spdlog_logger.hpp
cykit/cylogger/include/spdlog/async.h
cykit/cylogger/include/spdlog/async_logger-inl.h
cykit/cylogger/include/spdlog/async_logger.h
cykit/cylogger/include/spdlog/common-inl.h
cykit/cylogger/include/spdlog/common.h
cykit/cylogger/include/spdlog/formatter.h
cykit/cylogger/include/spdlog/fwd.h
cykit/cylogger/include/spdlog/logger-inl.h
cykit/cylogger/include/spdlog/logger.h
cykit/cylogger/include/spdlog/mdc.h
cykit/cylogger/include/spdlog/pattern_formatter-inl.h
cykit/cylogger/include/spdlog/pattern_formatter.h
cykit/cylogger/include/spdlog/spdlog-inl.h
cykit/cylogger/include/spdlog/spdlog.h
cykit/cylogger/include/spdlog/stopwatch.h
cykit/cylogger/include/spdlog/tweakme.h
cykit/cylogger/include/spdlog/version.h
cykit/cylogger/include/spdlog/cfg/argv.h
cykit/cylogger/include/spdlog/cfg/env.h
cykit/cylogger/include/spdlog/cfg/helpers-inl.h
cykit/cylogger/include/spdlog/cfg/helpers.h
cykit/cylogger/include/spdlog/details/backtracer-inl.h
cykit/cylogger/include/spdlog/details/backtracer.h
cykit/cylogger/include/spdlog/details/circular_q.h
cykit/cylogger/include/spdlog/details/console_globals.h
cykit/cylogger/include/spdlog/details/file_helper-inl.h
cykit/cylogger/include/spdlog/details/file_helper.h
cykit/cylogger/include/spdlog/details/fmt_helper.h
cykit/cylogger/include/spdlog/details/log_msg-inl.h
cykit/cylogger/include/spdlog/details/log_msg.h
cykit-0.0.6.dist-info/METADATA
cykit-0.0.6.dist-info/WHEEL
cykit-0.0.6.dist-info/top_level.txt
cykit-0.0.6.dist-info/RECORD
cykit-0.0.6.dist-info/licenses/LICENSE-APACHE
cykit-0.0.6.dist-info/licenses/LICENSE-MIT
