Metadata-Version: 2.4
Name: cykit
Version: 0.0.6
Summary: Cython utilities collection
Author-email: Tapan Hazarika <tapanhaz@gmail.com>
License: MIT OR Apache-2.0
Project-URL: Homepage, https://github.com/Tapanhaz/cykit
Project-URL: Source, https://github.com/Tapanhaz/cykit
Project-URL: Issues, https://github.com/Tapanhaz/cykit/issues
Classifier: Development Status :: 3 - Alpha
Classifier: Intended Audience :: Developers
Classifier: Programming Language :: Python :: 3
Classifier: Programming Language :: Python :: 3.9
Classifier: Programming Language :: Python :: 3.10
Classifier: Programming Language :: Python :: 3.11
Classifier: Programming Language :: Python :: 3.12
Classifier: Programming Language :: Python :: 3.13
Classifier: Programming Language :: Cython
Requires-Python: >=3.9
License-File: LICENSE-APACHE
License-File: LICENSE-MIT
Dynamic: license-file
